{
  "id": "region-l5ki",
  "name": "Region",
  "type": "STORAGE",
  "inputDatasets": [
    {
      "type": "NONE",
      "datasetId": "region",
      "name": "Region",
      "projectId": "{{ref(project.current.projectId)}}",
      "taskId": "onboarding_soure_landing-l5kd"
    }
  ],
  "datasetAttributes": {
    "materialized": "INHERIT",
    "hasHistory": "INHERIT",
    "hasLiveViews": "INHERIT",
    "hasChanges": "INHERIT",
    "hasStandardViewsWithHeaders": "INHERIT",
    "watermarkIncrementalSettings": "INHERIT",
    "createExternalArtifacts": "INHERIT"
  },
  "virtualDataset": false,
  "description": ""
}