{
  "id": "products-l5ji",
  "name": "products",
  "type": "STORAGE",
  "inputDatasets": [
    {
      "type": "NONE",
      "datasetId": "products",
      "name": "products",
      "projectId": "{{ref(project.current.projectId)}}",
      "taskId": "registered_data-l5je"
    }
  ],
  "datasetAttributes": {
    "materialized": "INHERIT",
    "hasHistory": "INHERIT",
    "hasLiveViews": "INHERIT",
    "hasChanges": "INHERIT",
    "hasStandardViewsWithHeaders": "INHERIT",
    "watermarkIncrementalSettings": "INHERIT",
    "createExternalArtifacts": "INHERIT"
  },
  "virtualDataset": false,
  "description": ""
}