{
  "id": "shippers-5iol",
  "name": "Shippers",
  "type": "STORAGE",
  "inputDatasets": [
    {
      "datasetId": "shippers",
      "name": "Shippers",
      "projectId": "{{ref(project.current.projectId)}}",
      "taskId": "landing-5iod"
    }
  ],
  "datasetAttributes": {
    "materialized": "INHERIT",
    "hasHistory": "INHERIT",
    "hasLiveViews": "INHERIT",
    "hasChanges": "INHERIT",
    "hasStandardViewsWithHeaders": "INHERIT",
    "watermarkIncrementalSettings": "INHERIT"
  },
  "virtualDataset": false
}