{
  "id": "prod_supp_flow-bkfi",
  "name": "prod_supp_flow",
  "type": "DATAFLOW",
  "inputDatasets": [
    {
      "datasetId": "products-bkfz",
      "projectId": "{{ref(project.current.projectId)}}",
      "taskId": "onboarding_storage-bkfw"
    },
    {
      "datasetId": "suppliers-bkfa",
      "projectId": "{{ref(project.current.projectId)}}",
      "taskId": "onboarding_storage-bkfw"
    }
  ],
  "datasetAttributes": {
    "materialized": "ON",
    "hasHistory": "INHERIT",
    "hasLiveViews": "INHERIT",
    "hasChanges": "INHERIT",
    "hasStandardViewsWithHeaders": "INHERIT",
    "watermarkIncrementalSettings": "INHERIT"
  },
  "dataflowDatasetSettings": {
    "dataflowId": "{{id(dataflow, prod_supp_flow)}}",
    "targetId": "d0a8657c-1c10-4a13-af0e-1b40814bfc29",
    "dataflowTargetState": "NOT_VALID",
    "incremental": false
  },
  "virtualDataset": false,
  "description": ""
}