{
  "id": "orders-xv68",
  "name": "Orders",
  "type": "TRANSFORM_MODEL_BASED",
  "inputDatasets": [
    {
      "type": "NONE",
      "datasetId": "orders-w4ss",
      "name": "Orders",
      "projectId": "{{project.rosie$_$databricks_multi_connections.projectId}}",
      "taskId": "onboarding_storage-w4so"
    }
  ],
  "datasetAttributes": {
    "materialized": "INHERIT",
    "hasHistory": "INHERIT",
    "hasLiveViews": "OFF",
    "hasChanges": "INHERIT",
    "hasStandardViewsWithHeaders": "INHERIT",
    "watermarkIncrementalSettings": "INHERIT"
  },
  "tableDef": {
    "name": "Orders",
    "columns": [
      {
        "name": "OrderID",
        "ordinal": 1,
        "nullable": false,
        "primaryKeyOrdinal": 1,
        "datatype": {
          "type": "INT4",
          "length": 0,
          "precision": 0,
          "scale": 0,
          "originalTypeFull": "INT"
        },
        "id": "orderid",
        "flags": "NONE",
        "properties": {
          "documentMetadata": false,
          "nesting": "NONE"
        }
      },
      {
        "name": "CustomerID",
        "ordinal": 2,
        "nullable": true,
        "primaryKeyOrdinal": 0,
        "datatype": {
          "type": "WSTRING",
          "length": 5,
          "precision": 0,
          "scale": 0,
          "originalTypeFull": "VARCHAR(5)"
        },
        "id": "customerid",
        "flags": "NONE",
        "properties": {
          "documentMetadata": false,
          "nesting": "NONE"
        }
      },
      {
        "name": "EmployeeID",
        "ordinal": 3,
        "nullable": true,
        "primaryKeyOrdinal": 0,
        "datatype": {
          "type": "INT4",
          "length": 0,
          "precision": 0,
          "scale": 0,
          "originalTypeFull": "INT"
        },
        "id": "employeeid",
        "flags": "NONE",
        "properties": {
          "documentMetadata": false,
          "nesting": "NONE"
        }
      },
      {
        "name": "OrderDate",
        "ordinal": 4,
        "nullable": true,
        "primaryKeyOrdinal": 0,
        "datatype": {
          "type": "DATETIME",
          "length": 0,
          "precision": 3,
          "scale": 0,
          "originalTypeFull": "TIMESTAMP"
        },
        "id": "orderdate",
        "flags": "NONE",
        "properties": {
          "documentMetadata": false,
          "nesting": "NONE"
        }
      },
      {
        "name": "RequiredDate",
        "ordinal": 5,
        "nullable": true,
        "primaryKeyOrdinal": 0,
        "datatype": {
          "type": "DATETIME",
          "length": 0,
          "precision": 3,
          "scale": 0,
          "originalTypeFull": "TIMESTAMP"
        },
        "id": "requireddate",
        "flags": "NONE",
        "properties": {
          "documentMetadata": false,
          "nesting": "NONE"
        }
      },
      {
        "name": "ShippedDate",
        "ordinal": 6,
        "nullable": true,
        "primaryKeyOrdinal": 0,
        "datatype": {
          "type": "DATETIME",
          "length": 0,
          "precision": 3,
          "scale": 0,
          "originalTypeFull": "TIMESTAMP"
        },
        "id": "shippeddate",
        "flags": "NONE",
        "properties": {
          "documentMetadata": false,
          "nesting": "NONE"
        }
      },
      {
        "name": "ShipVia",
        "ordinal": 7,
        "nullable": true,
        "primaryKeyOrdinal": 0,
        "datatype": {
          "type": "INT4",
          "length": 0,
          "precision": 0,
          "scale": 0,
          "originalTypeFull": "INT"
        },
        "id": "shipvia",
        "flags": "NONE",
        "properties": {
          "documentMetadata": false,
          "nesting": "NONE"
        }
      },
      {
        "name": "Freight",
        "ordinal": 8,
        "nullable": true,
        "primaryKeyOrdinal": 0,
        "datatype": {
          "type": "NUMERIC",
          "length": 0,
          "precision": 19,
          "scale": 4,
          "originalTypeFull": "DECIMAL(19,4)"
        },
        "id": "freight",
        "flags": "NONE",
        "properties": {
          "documentMetadata": false,
          "nesting": "NONE"
        }
      },
      {
        "name": "ShipName",
        "ordinal": 9,
        "nullable": true,
        "primaryKeyOrdinal": 0,
        "datatype": {
          "type": "WSTRING",
          "length": 40,
          "precision": 0,
          "scale": 0,
          "originalTypeFull": "VARCHAR(40)"
        },
        "id": "shipname",
        "flags": "NONE",
        "properties": {
          "documentMetadata": false,
          "nesting": "NONE"
        }
      },
      {
        "name": "ShipAddress",
        "ordinal": 10,
        "nullable": true,
        "primaryKeyOrdinal": 0,
        "datatype": {
          "type": "WSTRING",
          "length": 60,
          "precision": 0,
          "scale": 0,
          "originalTypeFull": "VARCHAR(60)"
        },
        "id": "shipaddress",
        "flags": "NONE",
        "properties": {
          "documentMetadata": false,
          "nesting": "NONE"
        }
      },
      {
        "name": "ShipCity",
        "ordinal": 11,
        "nullable": true,
        "primaryKeyOrdinal": 0,
        "datatype": {
          "type": "WSTRING",
          "length": 15,
          "precision": 0,
          "scale": 0,
          "originalTypeFull": "VARCHAR(15)"
        },
        "id": "shipcity",
        "flags": "NONE",
        "properties": {
          "documentMetadata": false,
          "nesting": "NONE"
        }
      },
      {
        "name": "ShipRegion",
        "ordinal": 12,
        "nullable": true,
        "primaryKeyOrdinal": 0,
        "datatype": {
          "type": "WSTRING",
          "length": 15,
          "precision": 0,
          "scale": 0,
          "originalTypeFull": "VARCHAR(15)"
        },
        "id": "shipregion",
        "flags": "NONE",
        "properties": {
          "documentMetadata": false,
          "nesting": "NONE"
        }
      },
      {
        "name": "ShipPostalCode",
        "ordinal": 13,
        "nullable": true,
        "primaryKeyOrdinal": 0,
        "datatype": {
          "type": "WSTRING",
          "length": 10,
          "precision": 0,
          "scale": 0,
          "originalTypeFull": "VARCHAR(10)"
        },
        "id": "shippostalcode",
        "flags": "NONE",
        "properties": {
          "documentMetadata": false,
          "nesting": "NONE"
        }
      },
      {
        "name": "ShipCountry",
        "ordinal": 14,
        "nullable": true,
        "primaryKeyOrdinal": 0,
        "datatype": {
          "type": "WSTRING",
          "length": 15,
          "precision": 0,
          "scale": 0,
          "originalTypeFull": "VARCHAR(15)"
        },
        "id": "shipcountry",
        "flags": "NONE",
        "properties": {
          "documentMetadata": false,
          "nesting": "NONE"
        }
      }
    ],
    "secureQri": "",
    "fullLoadOnly": false
  },
  "virtualDataset": false,
  "description": ""
}