{
  "id": "mdm_geography_country-7ps5",
  "name": "MDM_GEOGRAPHY_COUNTRY",
  "type": "STORAGE",
  "inputDatasets": [
    {
      "type": "NONE",
      "datasetId": "mdm_geography_country",
      "name": "MDM_GEOGRAPHY_COUNTRY",
      "projectId": "{{ref(project.current.projectId)}}",
      "taskId": "lnd_zoho_mdm-7ps1"
    }
  ],
  "datasetAttributes": {
    "materialized": "INHERIT",
    "hasHistory": "INHERIT",
    "hasLiveViews": "INHERIT",
    "hasChanges": "INHERIT",
    "hasStandardViewsWithHeaders": "INHERIT",
    "watermarkIncrementalSettings": "INHERIT",
    "createExternalArtifacts": "INHERIT"
  },
  "virtualDataset": false,
  "description": ""
}