{
  "includePatterns": [],
  "excludePatterns": [],
  "explicitlySelected": [
    {
      "database": "{{task.registered_data_1-5ise:ROSIE$_$Apr06_4_storage_1.database}}",
      "name": "Categories",
      "schema": "{{task.registered_data_1-5ise:ROSIE$_$Apr06_4_storage_1.schema}}",
      "type": "VIEW",
      "sourceTableId": "$registered_data$Mar12_3_storage_1_categories"
    },
    {
      "database": "{{task.registered_data_1-5ise:ROSIE$_$Apr06_4_storage_1.database}}",
      "name": "Customers",
      "schema": "{{task.registered_data_1-5ise:ROSIE$_$Apr06_4_storage_1.schema}}",
      "type": "VIEW",
      "sourceTableId": "$registered_data$Mar12_3_storage_1_customers"
    },
    {
      "database": "{{task.registered_data_1-5ise:ROSIE$_$Apr06_4_storage_1.database}}",
      "name": "Employees",
      "schema": "{{task.registered_data_1-5ise:ROSIE$_$Apr06_4_storage_1.schema}}",
      "type": "VIEW",
      "sourceTableId": "$registered_data$Mar12_3_storage_1_employees"
    },
    {
      "database": "{{task.registered_data_1-5ise:ROSIE$_$Apr06_4_storage_1.database}}",
      "name": "EmployeeTerritories",
      "schema": "{{task.registered_data_1-5ise:ROSIE$_$Apr06_4_storage_1.schema}}",
      "type": "VIEW",
      "sourceTableId": "$registered_data$Mar12_3_storage_1_employeeterritories"
    },
    {
      "database": "{{task.registered_data_1-5ise:ROSIE$_$Apr06_4_storage_1.database}}",
      "name": "Order Details",
      "schema": "{{task.registered_data_1-5ise:ROSIE$_$Apr06_4_storage_1.schema}}",
      "type": "VIEW",
      "sourceTableId": "$registered_data$Mar12_3_storage_1_order_details"
    },
    {
      "database": "{{task.registered_data_1-5ise:ROSIE$_$Apr06_4_storage_1.database}}",
      "name": "Orders",
      "schema": "{{task.registered_data_1-5ise:ROSIE$_$Apr06_4_storage_1.schema}}",
      "type": "VIEW",
      "sourceTableId": "$registered_data$Mar12_3_storage_1_orders"
    },
    {
      "database": "{{task.registered_data_1-5ise:ROSIE$_$Apr06_4_storage_1.database}}",
      "name": "Products",
      "schema": "{{task.registered_data_1-5ise:ROSIE$_$Apr06_4_storage_1.schema}}",
      "type": "VIEW",
      "sourceTableId": "$registered_data$Mar12_3_storage_1_products"
    },
    {
      "database": "{{task.registered_data_1-5ise:ROSIE$_$Apr06_4_storage_1.database}}",
      "name": "Region",
      "schema": "{{task.registered_data_1-5ise:ROSIE$_$Apr06_4_storage_1.schema}}",
      "type": "VIEW",
      "sourceTableId": "$registered_data$Mar12_3_storage_1_region"
    },
    {
      "database": "{{task.registered_data_1-5ise:ROSIE$_$Apr06_4_storage_1.database}}",
      "name": "Shippers",
      "schema": "{{task.registered_data_1-5ise:ROSIE$_$Apr06_4_storage_1.schema}}",
      "type": "VIEW",
      "sourceTableId": "$registered_data$Mar12_3_storage_1_shippers"
    },
    {
      "database": "{{task.registered_data_1-5ise:ROSIE$_$Apr06_4_storage_1.database}}",
      "name": "Suppliers",
      "schema": "{{task.registered_data_1-5ise:ROSIE$_$Apr06_4_storage_1.schema}}",
      "type": "VIEW",
      "sourceTableId": "$registered_data$Mar12_3_storage_1_suppliers"
    },
    {
      "database": "{{task.registered_data_1-5ise:ROSIE$_$Apr06_4_storage_1.database}}",
      "name": "Territories",
      "schema": "{{task.registered_data_1-5ise:ROSIE$_$Apr06_4_storage_1.schema}}",
      "type": "VIEW",
      "sourceTableId": "$registered_data$Mar12_3_storage_1_territories"
    }
  ]
}