{
  "type": "EXTERNAL_TABLE",
  "id": "$external_data_provider$_QCDI_TX_HIST_STG_BPCS_us_cic",
  "name": "LND_QCDI_TX_HIST_STG_BPCS_US_CIC",
  "tableDef": {
    "name": "US_CIC",
    "columns": [
      {
        "name": "DW_Id",
        "ordinal": 1,
        "nullable": false,
        "primaryKeyOrdinal": 1,
        "datatype": {
          "type": "NUMERIC",
          "length": 0,
          "precision": 38,
          "scale": 0,
          "originalTypeFull": ""
        },
        "id": "dw_id",
        "flags": "NONE"
      },
      {
        "name": "ICID",
        "ordinal": 2,
        "nullable": true,
        "primaryKeyOrdinal": 0,
        "datatype": {
          "type": "WSTRING",
          "length": 2,
          "precision": 0,
          "scale": 0,
          "originalTypeFull": ""
        },
        "id": "icid",
        "flags": "NONE"
      },
      {
        "name": "ICPROD",
        "ordinal": 3,
        "nullable": true,
        "primaryKeyOrdinal": 0,
        "datatype": {
          "type": "WSTRING",
          "length": 15,
          "precision": 0,
          "scale": 0,
          "originalTypeFull": ""
        },
        "id": "icprod",
        "flags": "NONE"
      },
      {
        "name": "ICFAC",
        "ordinal": 4,
        "nullable": true,
        "primaryKeyOrdinal": 0,
        "datatype": {
          "type": "WSTRING",
          "length": 2,
          "precision": 0,
          "scale": 0,
          "originalTypeFull": ""
        },
        "id": "icfac",
        "flags": "NONE"
      },
      {
        "name": "ICPLNC",
        "ordinal": 5,
        "nullable": true,
        "primaryKeyOrdinal": 0,
        "datatype": {
          "type": "WSTRING",
          "length": 1,
          "precision": 0,
          "scale": 0,
          "originalTypeFull": ""
        },
        "id": "icplnc",
        "flags": "NONE"
      },
      {
        "name": "ICLOTS",
        "ordinal": 6,
        "nullable": true,
        "primaryKeyOrdinal": 0,
        "datatype": {
          "type": "NUMERIC",
          "length": 0,
          "precision": 38,
          "scale": 3,
          "originalTypeFull": ""
        },
        "id": "iclots",
        "flags": "NONE"
      },
      {
        "name": "ICIOQ",
        "ordinal": 7,
        "nullable": true,
        "primaryKeyOrdinal": 0,
        "datatype": {
          "type": "NUMERIC",
          "length": 0,
          "precision": 38,
          "scale": 3,
          "originalTypeFull": ""
        },
        "id": "icioq",
        "flags": "NONE"
      },
      {
        "name": "ICMIN",
        "ordinal": 8,
        "nullable": true,
        "primaryKeyOrdinal": 0,
        "datatype": {
          "type": "NUMERIC",
          "length": 0,
          "precision": 38,
          "scale": 3,
          "originalTypeFull": ""
        },
        "id": "icmin",
        "flags": "NONE"
      },
      {
        "name": "ICLEAD",
        "ordinal": 9,
        "nullable": true,
        "primaryKeyOrdinal": 0,
        "datatype": {
          "type": "NUMERIC",
          "length": 0,
          "precision": 38,
          "scale": 0,
          "originalTypeFull": ""
        },
        "id": "iclead",
        "flags": "NONE"
      },
      {
        "name": "ICDLTR",
        "ordinal": 10,
        "nullable": true,
        "primaryKeyOrdinal": 0,
        "datatype": {
          "type": "NUMERIC",
          "length": 0,
          "precision": 38,
          "scale": 2,
          "originalTypeFull": ""
        },
        "id": "icdltr",
        "flags": "NONE"
      },
      {
        "name": "ICPCTK",
        "ordinal": 11,
        "nullable": true,
        "primaryKeyOrdinal": 0,
        "datatype": {
          "type": "NUMERIC",
          "length": 0,
          "precision": 38,
          "scale": 2,
          "originalTypeFull": ""
        },
        "id": "icpctk",
        "flags": "NONE"
      },
      {
        "name": "ICMAXR",
        "ordinal": 12,
        "nullable": true,
        "primaryKeyOrdinal": 0,
        "datatype": {
          "type": "NUMERIC",
          "length": 0,
          "precision": 38,
          "scale": 0,
          "originalTypeFull": ""
        },
        "id": "icmaxr",
        "flags": "NONE"
      },
      {
        "name": "ICMINR",
        "ordinal": 13,
        "nullable": true,
        "primaryKeyOrdinal": 0,
        "datatype": {
          "type": "NUMERIC",
          "length": 0,
          "precision": 38,
          "scale": 0,
          "originalTypeFull": ""
        },
        "id": "icminr",
        "flags": "NONE"
      },
      {
        "name": "ICTGQY",
        "ordinal": 14,
        "nullable": true,
        "primaryKeyOrdinal": 0,
        "datatype": {
          "type": "NUMERIC",
          "length": 0,
          "precision": 38,
          "scale": 3,
          "originalTypeFull": ""
        },
        "id": "ictgqy",
        "flags": "NONE"
      },
      {
        "name": "ICARRT",
        "ordinal": 15,
        "nullable": true,
        "primaryKeyOrdinal": 0,
        "datatype": {
          "type": "NUMERIC",
          "length": 0,
          "precision": 38,
          "scale": 3,
          "originalTypeFull": ""
        },
        "id": "icarrt",
        "flags": "NONE"
      },
      {
        "name": "ICMXIN",
        "ordinal": 16,
        "nullable": true,
        "primaryKeyOrdinal": 0,
        "datatype": {
          "type": "NUMERIC",
          "length": 0,
          "precision": 38,
          "scale": 3,
          "originalTypeFull": ""
        },
        "id": "icmxin",
        "flags": "NONE"
      },
      {
        "name": "ICDMTF",
        "ordinal": 17,
        "nullable": true,
        "primaryKeyOrdinal": 0,
        "datatype": {
          "type": "NUMERIC",
          "length": 0,
          "precision": 38,
          "scale": 0,
          "originalTypeFull": ""
        },
        "id": "icdmtf",
        "flags": "NONE"
      },
      {
        "name": "ICDMC1",
        "ordinal": 18,
        "nullable": true,
        "primaryKeyOrdinal": 0,
        "datatype": {
          "type": "WSTRING",
          "length": 1,
          "precision": 0,
          "scale": 0,
          "originalTypeFull": ""
        },
        "id": "icdmc1",
        "flags": "NONE"
      },
      {
        "name": "ICDMC2",
        "ordinal": 19,
        "nullable": true,
        "primaryKeyOrdinal": 0,
        "datatype": {
          "type": "WSTRING",
          "length": 1,
          "precision": 0,
          "scale": 0,
          "originalTypeFull": ""
        },
        "id": "icdmc2",
        "flags": "NONE"
      },
      {
        "name": "ICMBHD",
        "ordinal": 20,
        "nullable": true,
        "primaryKeyOrdinal": 0,
        "datatype": {
          "type": "NUMERIC",
          "length": 0,
          "precision": 38,
          "scale": 0,
          "originalTypeFull": ""
        },
        "id": "icmbhd",
        "flags": "NONE"
      },
      {
        "name": "ICMBDY",
        "ordinal": 21,
        "nullable": true,
        "primaryKeyOrdinal": 0,
        "datatype": {
          "type": "NUMERIC",
          "length": 0,
          "precision": 38,
          "scale": 0,
          "originalTypeFull": ""
        },
        "id": "icmbdy",
        "flags": "NONE"
      },
      {
        "name": "ICORDP",
        "ordinal": 22,
        "nullable": true,
        "primaryKeyOrdinal": 0,
        "datatype": {
          "type": "WSTRING",
          "length": 1,
          "precision": 0,
          "scale": 0,
          "originalTypeFull": ""
        },
        "id": "icordp",
        "flags": "NONE"
      },
      {
        "name": "ICMRP",
        "ordinal": 23,
        "nullable": true,
        "primaryKeyOrdinal": 0,
        "datatype": {
          "type": "WSTRING",
          "length": 1,
          "precision": 0,
          "scale": 0,
          "originalTypeFull": ""
        },
        "id": "icmrp",
        "flags": "NONE"
      },
      {
        "name": "ICPURC",
        "ordinal": 24,
        "nullable": true,
        "primaryKeyOrdinal": 0,
        "datatype": {
          "type": "WSTRING",
          "length": 1,
          "precision": 0,
          "scale": 0,
          "originalTypeFull": ""
        },
        "id": "icpurc",
        "flags": "NONE"
      },
      {
        "name": "ICMPSD",
        "ordinal": 25,
        "nullable": true,
        "primaryKeyOrdinal": 0,
        "datatype": {
          "type": "WSTRING",
          "length": 1,
          "precision": 0,
          "scale": 0,
          "originalTypeFull": ""
        },
        "id": "icmpsd",
        "flags": "NONE"
      },
      {
        "name": "ICCLAS",
        "ordinal": 26,
        "nullable": true,
        "primaryKeyOrdinal": 0,
        "datatype": {
          "type": "WSTRING",
          "length": 2,
          "precision": 0,
          "scale": 0,
          "originalTypeFull": ""
        },
        "id": "icclas",
        "flags": "NONE"
      },
      {
        "name": "ICPFDV",
        "ordinal": 27,
        "nullable": true,
        "primaryKeyOrdinal": 0,
        "datatype": {
          "type": "WSTRING",
          "length": 4,
          "precision": 0,
          "scale": 0,
          "originalTypeFull": ""
        },
        "id": "icpfdv",
        "flags": "NONE"
      },
      {
        "name": "ICACT",
        "ordinal": 28,
        "nullable": true,
        "primaryKeyOrdinal": 0,
        "datatype": {
          "type": "WSTRING",
          "length": 1,
          "precision": 0,
          "scale": 0,
          "originalTypeFull": ""
        },
        "id": "icact",
        "flags": "NONE"
      },
      {
        "name": "ICLEVL",
        "ordinal": 29,
        "nullable": true,
        "primaryKeyOrdinal": 0,
        "datatype": {
          "type": "NUMERIC",
          "length": 0,
          "precision": 38,
          "scale": 0,
          "originalTypeFull": ""
        },
        "id": "iclevl",
        "flags": "NONE"
      },
      {
        "name": "ICORDC",
        "ordinal": 30,
        "nullable": true,
        "primaryKeyOrdinal": 0,
        "datatype": {
          "type": "NUMERIC",
          "length": 0,
          "precision": 38,
          "scale": 5,
          "originalTypeFull": ""
        },
        "id": "icordc",
        "flags": "NONE"
      },
      {
        "name": "ICPODY",
        "ordinal": 31,
        "nullable": true,
        "primaryKeyOrdinal": 0,
        "datatype": {
          "type": "NUMERIC",
          "length": 0,
          "precision": 38,
          "scale": 0,
          "originalTypeFull": ""
        },
        "id": "icpody",
        "flags": "NONE"
      },
      {
        "name": "ICSCST",
        "ordinal": 32,
        "nullable": true,
        "primaryKeyOrdinal": 0,
        "datatype": {
          "type": "NUMERIC",
          "length": 0,
          "precision": 38,
          "scale": 5,
          "originalTypeFull": ""
        },
        "id": "icscst",
        "flags": "NONE"
      },
      {
        "name": "ICACST",
        "ordinal": 33,
        "nullable": true,
        "primaryKeyOrdinal": 0,
        "datatype": {
          "type": "NUMERIC",
          "length": 0,
          "precision": 38,
          "scale": 5,
          "originalTypeFull": ""
        },
        "id": "icacst",
        "flags": "NONE"
      },
      {
        "name": "ICFCST",
        "ordinal": 34,
        "nullable": true,
        "primaryKeyOrdinal": 0,
        "datatype": {
          "type": "NUMERIC",
          "length": 0,
          "precision": 38,
          "scale": 5,
          "originalTypeFull": ""
        },
        "id": "icfcst",
        "flags": "NONE"
      },
      {
        "name": "ICORGN",
        "ordinal": 35,
        "nullable": true,
        "primaryKeyOrdinal": 0,
        "datatype": {
          "type": "WSTRING",
          "length": 4,
          "precision": 0,
          "scale": 0,
          "originalTypeFull": ""
        },
        "id": "icorgn",
        "flags": "NONE"
      },
      {
        "name": "ICPVND",
        "ordinal": 36,
        "nullable": true,
        "primaryKeyOrdinal": 0,
        "datatype": {
          "type": "NUMERIC",
          "length": 0,
          "precision": 38,
          "scale": 0,
          "originalTypeFull": ""
        },
        "id": "icpvnd",
        "flags": "NONE"
      },
      {
        "name": "ICSVND",
        "ordinal": 37,
        "nullable": true,
        "primaryKeyOrdinal": 0,
        "datatype": {
          "type": "NUMERIC",
          "length": 0,
          "precision": 38,
          "scale": 0,
          "originalTypeFull": ""
        },
        "id": "icsvnd",
        "flags": "NONE"
      },
      {
        "name": "ICCOM",
        "ordinal": 38,
        "nullable": true,
        "primaryKeyOrdinal": 0,
        "datatype": {
          "type": "WSTRING",
          "length": 15,
          "precision": 0,
          "scale": 0,
          "originalTypeFull": ""
        },
        "id": "iccom",
        "flags": "NONE"
      },
      {
        "name": "ICFRMC",
        "ordinal": 39,
        "nullable": true,
        "primaryKeyOrdinal": 0,
        "datatype": {
          "type": "WSTRING",
          "length": 3,
          "precision": 0,
          "scale": 0,
          "originalTypeFull": ""
        },
        "id": "icfrmc",
        "flags": "NONE"
      },
      {
        "name": "ICREVL",
        "ordinal": 40,
        "nullable": true,
        "primaryKeyOrdinal": 0,
        "datatype": {
          "type": "WSTRING",
          "length": 2,
          "precision": 0,
          "scale": 0,
          "originalTypeFull": ""
        },
        "id": "icrevl",
        "flags": "NONE"
      },
      {
        "name": "ICFORM",
        "ordinal": 41,
        "nullable": true,
        "primaryKeyOrdinal": 0,
        "datatype": {
          "type": "WSTRING",
          "length": 15,
          "precision": 0,
          "scale": 0,
          "originalTypeFull": ""
        },
        "id": "icform",
        "flags": "NONE"
      },
      {
        "name": "ICBTCH",
        "ordinal": 42,
        "nullable": true,
        "primaryKeyOrdinal": 0,
        "datatype": {
          "type": "NUMERIC",
          "length": 0,
          "precision": 38,
          "scale": 3,
          "originalTypeFull": ""
        },
        "id": "icbtch",
        "flags": "NONE"
      },
      {
        "name": "ICMBWT",
        "ordinal": 43,
        "nullable": true,
        "primaryKeyOrdinal": 0,
        "datatype": {
          "type": "NUMERIC",
          "length": 0,
          "precision": 38,
          "scale": 3,
          "originalTypeFull": ""
        },
        "id": "icmbwt",
        "flags": "NONE"
      },
      {
        "name": "ICMUMB",
        "ordinal": 44,
        "nullable": true,
        "primaryKeyOrdinal": 0,
        "datatype": {
          "type": "WSTRING",
          "length": 2,
          "precision": 0,
          "scale": 0,
          "originalTypeFull": ""
        },
        "id": "icmumb",
        "flags": "NONE"
      },
      {
        "name": "ICSTYL",
        "ordinal": 45,
        "nullable": true,
        "primaryKeyOrdinal": 0,
        "datatype": {
          "type": "NUMERIC",
          "length": 0,
          "precision": 38,
          "scale": 2,
          "originalTypeFull": ""
        },
        "id": "icstyl",
        "flags": "NONE"
      },
      {
        "name": "ICPLN",
        "ordinal": 46,
        "nullable": true,
        "primaryKeyOrdinal": 0,
        "datatype": {
          "type": "WSTRING",
          "length": 2,
          "precision": 0,
          "scale": 0,
          "originalTypeFull": ""
        },
        "id": "icpln",
        "flags": "NONE"
      },
      {
        "name": "ICSTK",
        "ordinal": 47,
        "nullable": true,
        "primaryKeyOrdinal": 0,
        "datatype": {
          "type": "WSTRING",
          "length": 2,
          "precision": 0,
          "scale": 0,
          "originalTypeFull": ""
        },
        "id": "icstk",
        "flags": "NONE"
      },
      {
        "name": "ICFWA",
        "ordinal": 48,
        "nullable": true,
        "primaryKeyOrdinal": 0,
        "datatype": {
          "type": "WSTRING",
          "length": 1,
          "precision": 0,
          "scale": 0,
          "originalTypeFull": ""
        },
        "id": "icfwa",
        "flags": "NONE"
      },
      {
        "name": "ICBNDP",
        "ordinal": 49,
        "nullable": true,
        "primaryKeyOrdinal": 0,
        "datatype": {
          "type": "WSTRING",
          "length": 15,
          "precision": 0,
          "scale": 0,
          "originalTypeFull": ""
        },
        "id": "icbndp",
        "flags": "NONE"
      },
      {
        "name": "ICBNDC",
        "ordinal": 50,
        "nullable": true,
        "primaryKeyOrdinal": 0,
        "datatype": {
          "type": "WSTRING",
          "length": 15,
          "precision": 0,
          "scale": 0,
          "originalTypeFull": ""
        },
        "id": "icbndc",
        "flags": "NONE"
      },
      {
        "name": "ICBWIP",
        "ordinal": 51,
        "nullable": true,
        "primaryKeyOrdinal": 0,
        "datatype": {
          "type": "WSTRING",
          "length": 1,
          "precision": 0,
          "scale": 0,
          "originalTypeFull": ""
        },
        "id": "icbwip",
        "flags": "NONE"
      },
      {
        "name": "ICPMTH",
        "ordinal": 52,
        "nullable": true,
        "primaryKeyOrdinal": 0,
        "datatype": {
          "type": "WSTRING",
          "length": 2,
          "precision": 0,
          "scale": 0,
          "originalTypeFull": ""
        },
        "id": "icpmth",
        "flags": "NONE"
      },
      {
        "name": "ICCMTH",
        "ordinal": 53,
        "nullable": true,
        "primaryKeyOrdinal": 0,
        "datatype": {
          "type": "WSTRING",
          "length": 2,
          "precision": 0,
          "scale": 0,
          "originalTypeFull": ""
        },
        "id": "iccmth",
        "flags": "NONE"
      },
      {
        "name": "LastUpdate",
        "ordinal": 54,
        "nullable": true,
        "primaryKeyOrdinal": 0,
        "datatype": {
          "type": "DATETIME",
          "length": 0,
          "precision": 7,
          "scale": 0,
          "originalTypeFull": ""
        },
        "id": "lastupdate",
        "flags": "NONE"
      },
      {
        "name": "SourceCode",
        "ordinal": 55,
        "nullable": true,
        "primaryKeyOrdinal": 0,
        "datatype": {
          "type": "NUMERIC",
          "length": 0,
          "precision": 38,
          "scale": 0,
          "originalTypeFull": ""
        },
        "id": "sourcecode",
        "flags": "NONE"
      },
      {
        "name": "DW_Batch",
        "ordinal": 56,
        "nullable": true,
        "primaryKeyOrdinal": 0,
        "datatype": {
          "type": "NUMERIC",
          "length": 0,
          "precision": 38,
          "scale": 0,
          "originalTypeFull": ""
        },
        "id": "dw_batch",
        "flags": "NONE"
      },
      {
        "name": "DW_SourceCode",
        "ordinal": 57,
        "nullable": false,
        "primaryKeyOrdinal": 0,
        "datatype": {
          "type": "WSTRING",
          "length": 15,
          "precision": 0,
          "scale": 0,
          "originalTypeFull": ""
        },
        "id": "dw_sourcecode",
        "flags": "NONE"
      },
      {
        "name": "DW_TimeStamp",
        "ordinal": 58,
        "nullable": false,
        "primaryKeyOrdinal": 0,
        "datatype": {
          "type": "DATETIME",
          "length": 0,
          "precision": 3,
          "scale": 0,
          "originalTypeFull": ""
        },
        "id": "dw_timestamp",
        "flags": "NONE"
      }
    ],
    "secureQri": "",
    "fullLoadOnly": false
  }
}